carbonara_r2/__init__.py
carbonara_r2/__main__.py
carbonara_r2/main.py
carbonara_r2-1.0.4.dist-info/DESCRIPTION.rst
carbonara_r2-1.0.4.dist-info/METADATA
carbonara_r2-1.0.4.dist-info/RECORD
carbonara_r2-1.0.4.dist-info/WHEEL
carbonara_r2-1.0.4.dist-info/entry_points.txt
carbonara_r2-1.0.4.dist-info/metadata.json
carbonara_r2-1.0.4.dist-info/top_level.txt
