Metadata-Version: 2.0
Name: carbonara-r2
Version: 1.0.4
Summary: Carbonara Project Radare2 plugin
Home-page: https://github.com/Carbonara-Project/Carbonara-R2
Author: Andrea Fioraldi
Author-email: andreafioraldi@gmail.com
License: BSD 2-clause
Download-URL: https://github.com/Carbonara-Project/Carbonara-R2/archive/1.0.4.tar.gz
Platform: UNKNOWN
Requires-Dist: progressbar2
Requires-Dist: guanciale
